LICENSE.txt
MANIFEST.in
README.rst
setup.cfg
setup.py
ControlYourWay.egg-info/PKG-INFO
ControlYourWay.egg-info/SOURCES.txt
ControlYourWay.egg-info/dependency_links.txt
ControlYourWay.egg-info/requires.txt
ControlYourWay.egg-info/top_level.txt
ControlYourWay_p27/ControlYourWay_p27.py
ControlYourWay_p27/__init__.py
ControlYourWay_p3/ControlYourWay_p3.py
ControlYourWay_p3/__init__.py