Metadata-Version: 1.1
Name: ControlYourWay
Version: 1.2.0
Summary: Control Your Way Python Library
Home-page: https://www.controlyourway.com/Resources/PythonLibraryHelp
Author: Hubert Jetschko
Author-email: hubert@controlyourway.com
License: Other/Proprietary License
Keywords: IoT,Internet of Things communication platform
Platform: UNKNOWN
Classifier: Development Status :: 4 - Beta
Classifier: Intended Audience :: Developers
Classifier: Topic :: Communications
Classifier: License :: Other/Proprietary License
Classifier: Programming Language :: Python :: 2
Classifier: Programming Language :: Python :: 2.7
Classifier: Programming Language :: Python :: 3
Classifier: Programming Language :: Python :: 3.3
Classifier: Programming Language :: Python :: 3.4
Classifier: Programming Language :: Python :: 3.5
Classifier: Programming Language :: Python :: 3.6
